setu_mcp_kyc/__init__.py
setu_mcp_kyc/server.py
setu_mcp_kyc-0.1.1.dist-info/METADATA
setu_mcp_kyc-0.1.1.dist-info/WHEEL
setu_mcp_kyc-0.1.1.dist-info/entry_points.txt
setu_mcp_kyc-0.1.1.dist-info/RECORD
