Metadata-Version: 2.4
Name: setu_mcp_kyc
Version: 0.1.1
Summary: A MCP server for Setu KYC APIs providing PAN, GST, and name matching verification
Project-URL: Homepage, https://setu.co
Project-URL: Repository, https://github.com/SetuHQ/setu-mcps/tree/main/setu_mcp_kyc
Project-URL: Documentation, https://github.com/SetuHQ/setu-mcps/tree/main/setu_mcp_kyc
Author-email: Kaustav Banerjee <kaustav@setu.co>
License-Expression: MIT
Keywords: gst,mcp,pan,setu,setu_mcp_kyc,verification
Classifier: Development Status :: 4 - Beta
Classifier: Intended Audience :: Developers
Classifier: License :: OSI Approved :: MIT License
Classifier: Programming Language :: Python :: 3
Classifier: Programming Language :: Python :: 3.12
Classifier: Topic :: Software Development :: Libraries :: Python Modules
Requires-Python: >=3.12
Requires-Dist: httpx>=0.27.0
Requires-Dist: mcp>=1.2.0
Requires-Dist: python-dotenv>=1.0.0
